Metadata-Version: 2.1
Name: mpc
Version: 0.0.6
Summary: A fast and differentiable MPC solver for PyTorch.
Home-page: https://github.com/locuslab/mpc.pytorch
Author: Brandon Amos
Author-email: brandon.amos.cs@gmail.com
License: Apache 2.0
Platform: any
License-File: LICENSE.mit
